Workbook

Sheet Executive_Dashboard
A1: ADVANCED SALES & PROFITABILITY DASHBOARD
A2: Portfolio Project • 6,000 transactions • Jan 2024–Dec 2025 • Sample synthetic business data
A4: TOTAL SALES | D4: TOTAL PROFIT | G4: ORDERS | J4: AVG ORDER VALUE | M4: PROFIT MARGIN
A5: =SUM(Analysis_Data!L2:L6001) | D5: =SUM(Analysis_Data!N2:N6001) | G5: =COUNTA(Analysis_Data!A2:A6001) | J5: =IFERROR(SUM(Analysis_Data!L2:L6001)/COUNTA(Analysis_Data!A2:A6001),0) | M5: =IFERROR(SUM(Analysis_Data!N2:N6001)/SUM(Analysis_Data!L2:L6001),0)
A9: Monthly Trend | E9: Region Performance | I9: Category Performance | M9: Year Comparison
A10: Month | B10: Sales | C10: Profit | E10: Region | F10: Sales | G10: Profit | I10: Category | J10: Sales | K10: Profit | M10: Year | N10: Sales
A11: Jan | B11: =SUMIF(Analysis_Data!V$2:V$6001,A11,Analysis_Data!L$2:L$6001) | C11: =SUMIF(Analysis_Data!V$2:V$6001,A11,Analysis_Data!N$2:N$6001) | E11: North | F11: =SUMIF(Analysis_Data!C$2:C$6001,E11,Analysis_Data!L$2:L$6001) | G11: =SUMIF(Analysis_Data!C$2:C$6001,E11,Analysis_Data!N$2:N$6001) | I11: Accessories | J11: =SUMIF(Analysis_Data!G$2:G$6001,I11,Analysis_Data!L$2:L$6001) | K11: =SUMIF(Analysis_Data!G$2:G$6001,I11,Analysis_Data!N$2:N$6001) | M11: 2024 | N11: =SUMIF(Analysis_Data!T$2:T$6001,M11,Analysis_Data!L$2:L$6001)
A12: Feb | B12: =SUMIF(Analysis_Data!V$2:V$6001,A12,Analysis_Data!L$2:L$6001) | C12: =SUMIF(Analysis_Data!V$2:V$6001,A12,Analysis_Data!N$2:N$6001) | E12: South | F12: =SUMIF(Analysis_Data!C$2:C$6001,E12,Analysis_Data!L$2:L$6001) | G12: =SUMIF(Analysis_Data!C$2:C$6001,E12,Analysis_Data!N$2:N$6001) | I12: Furniture | J12: =SUMIF(Analysis_Data!G$2:G$6001,I12,Analysis_Data!L$2:L$6001) | K12: =SUMIF(Analysis_Data!G$2:G$6001,I12,Analysis_Data!N$2:N$6001) | M12: 2025 | N12: =SUMIF(Analysis_Data!T$2:T$6001,M12,Analysis_Data!L$2:L$6001)
A13: Mar | B13: =SUMIF(Analysis_Data!V$2:V$6001,A13,Analysis_Data!L$2:L$6001) | C13: =SUMIF(Analysis_Data!V$2:V$6001,A13,Analysis_Data!N$2:N$6001) | E13: East | F13: =SUMIF(Analysis_Data!C$2:C$6001,E13,Analysis_Data!L$2:L$6001) | G13: =SUMIF(Analysis_Data!C$2:C$6001,E13,Analysis_Data!N$2:N$6001) | I13: Office Supplies | J13: =SUMIF(Analysis_Data!G$2:G$6001,I13,Analysis_Data!L$2:L$6001) | K13: =SUMIF(Analysis_Data!G$2:G$6001,I13,Analysis_Data!N$2:N$6001)
A14: Apr | B14: =SUMIF(Analysis_Data!V$2:V$6001,A14,Analysis_Data!L$2:L$6001) | C14: =SUMIF(Analysis_Data!V$2:V$6001,A14,Analysis_Data!N$2:N$6001) | E14: West | F14: =SUMIF(Analysis_Data!C$2:C$6001,E14,Analysis_Data!L$2:L$6001) | G14: =SUMIF(Analysis_Data!C$2:C$6001,E14,Analysis_Data!N$2:N$6001) | I14: Technology | J14: =SUMIF(Analysis_Data!G$2:G$6001,I14,Analysis_Data!L$2:L$6001) | K14: =SUMIF(Analysis_Data!G$2:G$6001,I14,Analysis_Data!N$2:N$6001)
A15: May | B15: =SUMIF(Analysis_Data!V$2:V$6001,A15,Analysis_Data!L$2:L$6001) | C15: =SUMIF(Analysis_Data!V$2:V$6001,A15,Analysis_Data!N$2:N$6001) | E15: Central | F15: =SUMIF(Analysis_Data!C$2:C$6001,E15,Analysis_Data!L$2:L$6001) | G15: =SUMIF(Analysis_Data!C$2:C$6001,E15,Analysis_Data!N$2:N$6001)
A16: Jun | B16: =SUMIF(Analysis_Data!V$2:V$6001,A16,Analysis_Data!L$2:L$6001) | C16: =SUMIF(Analysis_Data!V$2:V$6001,A16,Analysis_Data!N$2:N$6001)
A17: Jul | B17: =SUMIF(Analysis_Data!V$2:V$6001,A17,Analysis_Data!L$2:L$6001) | C17: =SUMIF(Analysis_Data!V$2:V$6001,A17,Analysis_Data!N$2:N$6001)
A18: Aug | B18: =SUMIF(Analysis_Data!V$2:V$6001,A18,Analysis_Data!L$2:L$6001) | C18: =SUMIF(Analysis_Data!V$2:V$6001,A18,Analysis_Data!N$2:N$6001)
A19: Sep | B19: =SUMIF(Analysis_Data!V$2:V$6001,A19,Analysis_Data!L$2:L$6001) | C19: =SUMIF(Analysis_Data!V$2:V$6001,A19,Analysis_Data!N$2:N$6001)
A20: Oct | B20: =SUMIF(Analysis_Data!V$2:V$6001,A20,Analysis_Data!L$2:L$6001) | C20: =SUMIF(Analysis_Data!V$2:V$6001,A20,Analysis_Data!N$2:N$6001)
A21: Nov | B21: =SUMIF(Analysis_Data!V$2:V$6001,A21,Analysis_Data!L$2:L$6001) | C21: =SUMIF(Analysis_Data!V$2:V$6001,A21,Analysis_Data!N$2:N$6001)
A22: Dec | B22: =SUMIF(Analysis_Data!V$2:V$6001,A22,Analysis_Data!L$2:L$6001) | C22: =SUMIF(Analysis_Data!V$2:V$6001,A22,Analysis_Data!N$2:N$6001)

Sheet Raw_Data
A1: Order_ID | B1: Order_Date | C1: Region | D1: City | E1: Customer_Segment | F1: Sales_Channel | G1: Category | H1: Product | I1: Quantity | J1: Unit_Price | K1: Discount_Rate | L1: Sales | M1: Cost | N1: Profit | O1: Payment_Method | P1: Sales_Rep | Q1: Customer_ID | R1: Ship_Days | S1: Returned
A2: ORD-2511-00001 | B2: 45988 | C2: East | D2: Bhubaneswar | E2: Consumer | F2: Retail Store | G2: Technology | H2: Tablet | I2: 1 | J2: 20915.36 | K2: 0.15 | L2: 17778.06 | M2: 17359.75 | N2: 418.31 | O2: UPI | P2: Meera Joshi | Q2: CUST-0199 | R2: 3 | S2: No
A3: ORD-2511-00002 | B3: 45965 | C3: Central | D3: Bhopal | E3: Education | F3: Online | G3: Furniture | H3: Office Chair | I3: 5 | J3: 6822.94 | K3: 0.1 | L3: 30703.23 | M3: 23539.14 | N3: 7164.09 | O3: Cash | P3: Diya Patel | Q3: CUST-0377 | R3: 2 | S3: No
A4: ORD-2402-00003 | B4: 45350 | C4: North | D4: Jaipur | E4: Small Business | F4: Online | G4: Technology | H4: Headphones | I4: 3 | J4: 2866.75 | K4: 0.2 | L4: 6880.2 | M4: 6364.18 | N4: 516.02 | O4: Credit Card | P4: Vivaan Gupta | Q4: CUST-0631 | R4: 5 | S4: Yes
A5: ORD-2503-00004 | B5: 45728 | C5: West | D5: Mumbai | E5: Consumer | F5: Online | G5: Technology | H5: Headphones | I5: 6 | J5: 2648.12 | K5: 0.2 | L5: 12710.98 | M5: 11757.65 | N5: 953.33 | O5: Debit Card | P5: Diya Patel | Q5: CUST-0305 | R5: 4 | S5: No
A6: ORD-2403-00005 | B6: 45368 | C6: West | D6: Pune | E6: Consumer | F6: Partner | G6: Accessories | H6: Mouse | I6: 12 | J6: 778.92 | K6: 0.1 | L6: 8412.34 | M6: 6169.05 | N6: 2243.29 | O6: UPI | P6: Tara Kapoor | Q6: CUST-0388 | R6: 1 | S6: No
A7: ORD-2408-00006 | B7: 45535 | C7: North | D7: Jaipur | E7: Small Business | F7: Online | G7: Furniture | H7: Cabinet | I7: 6 | J7: 9427.88 | K7: 0.1 | L7: 50910.55 | M7: 44122.48 | N7: 6788.07 | O7: Debit Card | P7: Anaya Rao | Q7: CUST-0015 | R7: 6 | S7: No
A8: ORD-2410-00007 | B8: 45591 | C8: Central | D8: Bhopal | E8: Small Business | F8: Direct Sales | G8: Technology | H8: Monitor | I8: 5 | J8: 13297.11 | K8: 0.15 | L8: 56512.72 | M8: 53188.44 | N8: 3324.28 | O8: UPI | P8: Anaya Rao | Q8: CUST-0747 | R8: 3 | S8: No
A9: ORD-2411-00008 | B9: 45615 | C9: Central | D9: Raipur | E9: Education | F9: Partner | G9: Furniture | H9: Bookshelf | I9: 5 | J9: 5719.65 | K9: 0.15 | L9: 24308.51 | M9: 20876.72 | N9: 3431.79 | O9: Debit Card | P9: Kabir Singh | Q9: CUST-0155 | R9: 4 | S9: No
A10: ORD-2410-00009 | B10: 45590 | C10: West | D10: Pune | E10: Education | F10: Partner | G10: Technology | H10: Laptop | I10: 1 | J10: 49948.67 | K10: 0.1 | L10: 44953.8 | M10: 42955.86 | N10: 1997.94 | O10: Cash | P10: Ishaan Mehta | Q10: CUST-0236 | R10: 6 | S10: No
A11: ORD-2505-00010 | B11: 45791 | C11: West | D11: Pune | E11: Education | F11: Partner | G11: Technology | H11: Headphones | I11: 3 | J11: 2970.97 | K11: 0.25 | L11: 6684.68 | M11: 6595.55 | N11: 89.13 | O11: UPI | P11: Kabir Singh | Q11: CUST-0415 | R11: 3 | S11: No
A12: ORD-2404-00011 | B12: 45403 | C12: Central | D12: Indore | E12: Education | F12: Online | G12: Technology | H12: Laptop | I12: 5 | J12: 44256.22 | K12: 0.15 | L12: 188088.93 | M12: 190301.75 | N12: -2212.82 | O12: Cash | P12: Tara Kapoor | Q12: CUST-0023 | R12: 2 | S12: No
A13: ORD-2407-00012 | B13: 45498 | C13: West | D13: Mumbai | E13: Corporate | F13: Direct Sales | G13: Technology | H13: Printer | I13: 10 | J13: 11596.26 | K13: 0.1 | L13: 104366.34 | M13: 95089.33 | N13: 9277.01 | O13: Net Banking | P13: Sara Khan | Q13: CUST-0192 | R13: 6 | S13: No
... A6001: ORD-2402-06000 | B6001: 45349 | C6001: West | D6001: Ahmedabad | E6001: Small Business | F6001: Online | G6001: Office Supplies | H6001: Marker Set | I6001: 3 | J6001: 240.91 | K6001: 0 | L6001: 722.73 | M6001: 469.77 | N6001: 252.96 | O6001: Cash | P6001: Sara Khan | Q6001: CUST-0787 | R6001: 3 | S6001: Yes

Sheet Analysis_Data
A1: Order_ID | B1: Order_Date | C1: Region | D1: City | E1: Customer_Segment | F1: Sales_Channel | G1: Category | H1: Product | I1: Quantity | J1: Unit_Price | K1: Discount_Rate | L1: Sales | M1: Cost | N1: Profit | O1: Payment_Method | P1: Sales_Rep | Q1: Customer_ID | R1: Ship_Days | S1: Returned | T1: Year | U1: Month_No | V1: Month | W1: Profit_Margin | X1: Discount_Band | Y1: Order_Value_Band | Z1: Delivery_Status
A2: =Raw_Data!A2 | B2: =Raw_Data!B2 | C2: =Raw_Data!C2 | D2: =Raw_Data!D2 | E2: =Raw_Data!E2 | F2: =Raw_Data!F2 | G2: =Raw_Data!G2 | H2: =Raw_Data!H2 | ... S2: =Raw_Data!S2 | T2: =YEAR(B2) | U2: =MONTH(B2) | V2: =TEXT(B2,"mmm") | W2: =IFERROR(N2/L2,0) | X2: =IF(K2=0,"No Discount",IF(K2<=5%,"Low",IF(K2<=15%,"Medium","High"))) | Y2: =IF(L2>=20000,"High Value",IF(L2>=5000,"Medium Value","Low Value")) | Z2: =IF(R2<=3,"Fast",IF(R2<=5,"On Time","Delayed"))
A3: =Raw_Data!A3 | B3: =Raw_Data!B3 | C3: =Raw_Data!C3 | D3: =Raw_Data!D3 | E3: =Raw_Data!E3 | F3: =Raw_Data!F3 | G3: =Raw_Data!G3 | H3: =Raw_Data!H3 | ... S3: =Raw_Data!S3 | T3: =YEAR(B3) | U3: =MONTH(B3) | V3: =TEXT(B3,"mmm") | W3: =IFERROR(N3/L3,0) | X3: =IF(K3=0,"No Discount",IF(K3<=5%,"Low",IF(K3<=15%,"Medium","High"))) | Y3: =IF(L3>=20000,"High Value",IF(L3>=5000,"Medium Value","Low Value")) | Z3: =IF(R3<=3,"Fast",IF(R3<=5,"On Time","Delayed"))
A4: =Raw_Data!A4 | B4: =Raw_Data!B4 | C4: =Raw_Data!C4 | D4: =Raw_Data!D4 | E4: =Raw_Data!E4 | F4: =Raw_Data!F4 | G4: =Raw_Data!G4 | H4: =Raw_Data!H4 | ... S4: =Raw_Data!S4 | T4: =YEAR(B4) | U4: =MONTH(B4) | V4: =TEXT(B4,"mmm") | W4: =IFERROR(N4/L4,0) | X4: =IF(K4=0,"No Discount",IF(K4<=5%,"Low",IF(K4<=15%,"Medium","High"))) | Y4: =IF(L4>=20000,"High Value",IF(L4>=5000,"Medium Value","Low Value")) | Z4: =IF(R4<=3,"Fast",IF(R4<=5,"On Time","Delayed"))
A5: =Raw_Data!A5 | B5: =Raw_Data!B5 | C5: =Raw_Data!C5 | D5: =Raw_Data!D5 | E5: =Raw_Data!E5 | F5: =Raw_Data!F5 | G5: =Raw_Data!G5 | H5: =Raw_Data!H5 | ... S5: =Raw_Data!S5 | T5: =YEAR(B5) | U5: =MONTH(B5) | V5: =TEXT(B5,"mmm") | W5: =IFERROR(N5/L5,0) | X5: =IF(K5=0,"No Discount",IF(K5<=5%,"Low",IF(K5<=15%,"Medium","High"))) | Y5: =IF(L5>=20000,"High Value",IF(L5>=5000,"Medium Value","Low Value")) | Z5: =IF(R5<=3,"Fast",IF(R5<=5,"On Time","Delayed"))
A6: =Raw_Data!A6 | B6: =Raw_Data!B6 | C6: =Raw_Data!C6 | D6: =Raw_Data!D6 | E6: =Raw_Data!E6 | F6: =Raw_Data!F6 | G6: =Raw_Data!G6 | H6: =Raw_Data!H6 | ... S6: =Raw_Data!S6 | T6: =YEAR(B6) | U6: =MONTH(B6) | V6: =TEXT(B6,"mmm") | W6: =IFERROR(N6/L6,0) | X6: =IF(K6=0,"No Discount",IF(K6<=5%,"Low",IF(K6<=15%,"Medium","High"))) | Y6: =IF(L6>=20000,"High Value",IF(L6>=5000,"Medium Value","Low Value")) | Z6: =IF(R6<=3,"Fast",IF(R6<=5,"On Time","Delayed"))
A7: =Raw_Data!A7 | B7: =Raw_Data!B7 | C7: =Raw_Data!C7 | D7: =Raw_Data!D7 | E7: =Raw_Data!E7 | F7: =Raw_Data!F7 | G7: =Raw_Data!G7 | H7: =Raw_Data!H7 | ... S7: =Raw_Data!S7 | T7: =YEAR(B7) | U7: =MONTH(B7) | V7: =TEXT(B7,"mmm") | W7: =IFERROR(N7/L7,0) | X7: =IF(K7=0,"No Discount",IF(K7<=5%,"Low",IF(K7<=15%,"Medium","High"))) | Y7: =IF(L7>=20000,"High Value",IF(L7>=5000,"Medium Value","Low Value")) | Z7: =IF(R7<=3,"Fast",IF(R7<=5,"On Time","Delayed"))
A8: =Raw_Data!A8 | B8: =Raw_Data!B8 | C8: =Raw_Data!C8 | D8: =Raw_Data!D8 | E8: =Raw_Data!E8 | F8: =Raw_Data!F8 | G8: =Raw_Data!G8 | H8: =Raw_Data!H8 | ... S8: =Raw_Data!S8 | T8: =YEAR(B8) | U8: =MONTH(B8) | V8: =TEXT(B8,"mmm") | W8: =IFERROR(N8/L8,0) | X8: =IF(K8=0,"No Discount",IF(K8<=5%,"Low",IF(K8<=15%,"Medium","High"))) | Y8: =IF(L8>=20000,"High Value",IF(L8>=5000,"Medium Value","Low Value")) | Z8: =IF(R8<=3,"Fast",IF(R8<=5,"On Time","Delayed"))
A9: =Raw_Data!A9 | B9: =Raw_Data!B9 | C9: =Raw_Data!C9 | D9: =Raw_Data!D9 | E9: =Raw_Data!E9 | F9: =Raw_Data!F9 | G9: =Raw_Data!G9 | H9: =Raw_Data!H9 | ... S9: =Raw_Data!S9 | T9: =YEAR(B9) | U9: =MONTH(B9) | V9: =TEXT(B9,"mmm") | W9: =IFERROR(N9/L9,0) | X9: =IF(K9=0,"No Discount",IF(K9<=5%,"Low",IF(K9<=15%,"Medium","High"))) | Y9: =IF(L9>=20000,"High Value",IF(L9>=5000,"Medium Value","Low Value")) | Z9: =IF(R9<=3,"Fast",IF(R9<=5,"On Time","Delayed"))
A10: =Raw_Data!A10 | B10: =Raw_Data!B10 | C10: =Raw_Data!C10 | D10: =Raw_Data!D10 | E10: =Raw_Data!E10 | F10: =Raw_Data!F10 | G10: =Raw_Data!G10 | H10: =Raw_Data!H10 | ... S10: =Raw_Data!S10 | T10: =YEAR(B10) | U10: =MONTH(B10) | V10: =TEXT(B10,"mmm") | W10: =IFERROR(N10/L10,0) | X10: =IF(K10=0,"No Discount",IF(K10<=5%,"Low",IF(K10<=15%,"Medium","High"))) | Y10: =IF(L10>=20000,"High Value",IF(L10>=5000,"Medium Value","Low Value")) | Z10: =IF(R10<=3,"Fast",IF(R10<=5,"On Time","Delayed"))
A11: =Raw_Data!A11 | B11: =Raw_Data!B11 | C11: =Raw_Data!C11 | D11: =Raw_Data!D11 | E11: =Raw_Data!E11 | F11: =Raw_Data!F11 | G11: =Raw_Data!G11 | H11: =Raw_Data!H11 | ... S11: =Raw_Data!S11 | T11: =YEAR(B11) | U11: =MONTH(B11) | V11: =TEXT(B11,"mmm") | W11: =IFERROR(N11/L11,0) | X11: =IF(K11=0,"No Discount",IF(K11<=5%,"Low",IF(K11<=15%,"Medium","High"))) | Y11: =IF(L11>=20000,"High Value",IF(L11>=5000,"Medium Value","Low Value")) | Z11: =IF(R11<=3,"Fast",IF(R11<=5,"On Time","Delayed"))
A12: =Raw_Data!A12 | B12: =Raw_Data!B12 | C12: =Raw_Data!C12 | D12: =Raw_Data!D12 | E12: =Raw_Data!E12 | F12: =Raw_Data!F12 | G12: =Raw_Data!G12 | H12: =Raw_Data!H12 | ... S12: =Raw_Data!S12 | T12: =YEAR(B12) | U12: =MONTH(B12) | V12: =TEXT(B12,"mmm") | W12: =IFERROR(N12/L12,0) | X12: =IF(K12=0,"No Discount",IF(K12<=5%,"Low",IF(K12<=15%,"Medium","High"))) | Y12: =IF(L12>=20000,"High Value",IF(L12>=5000,"Medium Value","Low Value")) | Z12: =IF(R12<=3,"Fast",IF(R12<=5,"On Time","Delayed"))
A13: =Raw_Data!A13 | B13: =Raw_Data!B13 | C13: =Raw_Data!C13 | D13: =Raw_Data!D13 | E13: =Raw_Data!E13 | F13: =Raw_Data!F13 | G13: =Raw_Data!G13 | H13: =Raw_Data!H13 | ... S13: =Raw_Data!S13 | T13: =YEAR(B13) | U13: =MONTH(B13) | V13: =TEXT(B13,"mmm") | W13: =IFERROR(N13/L13,0) | X13: =IF(K13=0,"No Discount",IF(K13<=5%,"Low",IF(K13<=15%,"Medium","High"))) | Y13: =IF(L13>=20000,"High Value",IF(L13>=5000,"Medium Value","Low Value")) | Z13: =IF(R13<=3,"Fast",IF(R13<=5,"On Time","Delayed"))
... A6001: =Raw_Data!A6001 | B6001: =Raw_Data!B6001 | C6001: =Raw_Data!C6001 | D6001: =Raw_Data!D6001 | E6001: =Raw_Data!E6001 | F6001: =Raw_Data!F6001 | G6001: =Raw_Data!G6001 | H6001: =Raw_Data!H6001 | ... S6001: =Raw_Data!S6001 | T6001: =YEAR(B6001) | U6001: =MONTH(B6001) | V6001: =TEXT(B6001,"mmm") | W6001: =IFERROR(N6001/L6001,0) | X6001: =IF(K6001=0,"No Discount",IF(K6001<=5%,"Low",IF(K6001<=15%,"Medium","High"))) | Y6001: =IF(L6001>=20000,"High Value",IF(L6001>=5000,"Medium Value","Low Value")) | Z6001: =IF(R6001<=3,"Fast",IF(R6001<=5,"On Time","Delayed"))

Sheet Advanced_Formula_Lab
A1: Skill | B1: Example formula (Excel Table / Microsoft 365) | C1: Purpose / notes | D1: Practice task
A2: SUMIFS | B2: =SUMIFS(AnalysisData[Sales],AnalysisData[Region],"North",AnalysisData[Category],"Technology") | C2: Multi-condition aggregation. | D2: Calculate sales for West + Furniture.
A3: COUNTIFS | B3: =COUNTIFS(AnalysisData[Returned],"Yes",AnalysisData[Region],"South") | C3: Count rows meeting multiple conditions. | D3: Count returns by sales channel.
A4: XLOOKUP | B4: =XLOOKUP(A2,AnalysisData[Order_ID],AnalysisData[Product],"Not Found") | C4: Look up product by Order ID; type an Order ID into A2. | D4: Return customer, sales and profit for an order.
A5: INDEX/MATCH | B5: =INDEX(AnalysisData[Sales],MATCH(A2,AnalysisData[Order_ID],0)) | C5: Alternative lookup compatible with older Excel versions. | D5: Look up sales for an order ID.
A6: FILTER | B6: =FILTER(AnalysisData[[Order_ID]:[Profit]],AnalysisData[Region]="North","No rows") | C6: Dynamic array returns all North-region records. | D6: Filter returned orders.
A7: LET | B7: =LET(total,SUM(AnalysisData[Sales]),profit,SUM(AnalysisData[Profit]),profit/total) | C7: Name intermediate calculations for readability. | D7: Calculate average sales per customer.
A8: IFERROR | B8: =IFERROR(Profit/Sales,0) | C8: Avoid visible formula errors when denominator is zero. | D8: Protect a ratio calculation.
A9: Dynamic month list | B9: =SORT(UNIQUE(AnalysisData[Month])) | C9: Create a unique sorted list; dynamic arrays need Microsoft 365/Excel 2021+. | D9: Build a dropdown list from unique regions.
A10: SUMPRODUCT | B10: =SUMPRODUCT((AnalysisData[Region]="North")*(AnalysisData[Sales_Channel]="Online")*AnalysisData[Sales]) | C10: Conditional calculation without a PivotTable. | D10: Calculate sales for East + Partner.
A11: RANK.EQ | B11: =RANK.EQ(B2,$B$2:$B$6,0) | C11: Rank regions/products based on a metric. | D11: Rank the five regions by sales.

Sheet What_If_Analysis
A1: WHAT-IF ANALYSIS: DISCOUNT AND PROFITABILITY
A2: Input / Output | B2: Value | C2: Explanation | D2: Decision prompt
A3: Baseline Sales | B3: =SUM(Analysis_Data!L2:L6001) | C3: Current total sales from transaction data. | D3: What is the baseline?
A4: Baseline Profit | B4: =SUM(Analysis_Data!N2:N6001) | C4: Current estimated profit. | D4: What is the baseline?
A5: Additional discount rate | B5: 0.02 | C5: Editable assumption: extra discount applied to all sales. | D5: Test 0%, 2%, 5%.
A6: Estimated sales after extra discount | B6: =B2*(1-B4) | C6: Simplified assumption: volume remains unchanged. | D6: Would discounting reduce revenue?
A7: Estimated profit after extra discount | B7: =B3-B2*B4 | C7: Simplified model assumes cost and quantity remain unchanged. | D7: Does the extra discount reduce profit?
A8: Profit change | B8: =B6-B3 | C8: Estimated profit after discount minus baseline profit. | D8: Would you approve this discount?
A9: Target profit margin | B9: 0.2 | C9: Editable management target. | D9: Change the target and compare.
A10: Baseline profit margin | B10: =IFERROR(B3/B2,0) | C10: Baseline profit divided by baseline sales. | D10: Is baseline above target?
A11: Target met? | B11: =IF(B9>=B8,"Yes","No") | C11: Compares baseline margin with target. | D11: What actions would improve margin?

Sheet Portfolio_Guide
A1: Phase | B1: Task | C1: Instructions | D1: Deliverable / validation
A2: 1. Business question | B2: Define purpose | C2: Measure sales, profit, margin, customer segment, product/category, region, channel, returns and delivery performance. | D2: One-sentence problem statement.
A3: 2. Data quality | B3: Validate records | C3: Check duplicate Order_ID, blanks, dates, numeric fields, discount bounds, negative sales/profit and inconsistent labels. Use Data > Remove Duplicates on a copy only. | D3: Document any issues and corrections.
A4: 3. Power Query | B4: Build repeatable cleaning | C4: Data > From Table/Range; set data types, trim/clean text, replace inconsistent labels, remove duplicates if valid, add Year/Month columns; Close & Load. | D4: Refreshable query; explain applied steps.
A5: 4. Data model | B5: Create relationships (optional) | C5: For advanced practice, create separate Date, Product, Region and Customer dimension tables; use Data Model and relationships if your Excel version supports it. | D5: Star-schema model diagram.
A6: 5. KPI definitions | B6: Document calculations | C6: Sales=net sales after discount; Profit=Sales-Cost; Profit Margin=Profit/Sales; AOV=Sales/Orders; Return Rate=Returned orders/Orders. | D6: KPI definition table.
A7: 6. PivotTables | B7: Analyze performance | C7: Create PivotTables for month/year, region, category/product, channel, customer segment, return status and delivery status. | D7: PivotTables on separate analysis sheets.
A8: 7. Dashboard | B8: Build interactions | C8: Use KPI cards and PivotCharts; add slicers for Region, Category, Channel and Segment. Connect each slicer to relevant PivotTables via Report Connections. | D8: Interactive executive dashboard.
A9: 8. Advanced formulas | B9: Practice analysis | C9: Use SUMIFS, COUNTIFS, XLOOKUP, INDEX/MATCH, FILTER, LET, SUMPRODUCT, IFERROR, RANK.EQ and UNIQUE as supported. | D9: Formula lab completed.
A10: 9. What-if | B10: Test a business decision | C10: Adjust additional discount and target margin in What_If_Analysis. Explain limitations: this simplified model assumes no demand response and unchanged cost. | D10: Recommendation with assumptions.
A11: 10. QA | B11: Reconcile dashboard | C11: Compare total sales/profit on dashboard to SUM of Analysis_Data columns. Confirm date filters, slicers, and charts update; refresh all queries and PivotTables. | D11: QA checklist signed off.
A12: 11. Insight writing | B12: Summarize evidence | C12: Report top region/category, month-over-month or year-over-year change, margin risks, return rate and delivery performance. Include exact numbers from your analysis. | D12: 3–5 findings and 2 recommendations.
A13: 12. Portfolio packaging | B13: Publish safely | C13: Save workbook, include screenshots, a short README, KPI definitions, methodology, limitations and recommendations. Synthetic dataset: do not describe it as real company data. | D13: Portfolio link on resume.

Sheet Business_Insights
A1: Business question | B1: Analysis method | C1: Finding (fill after analysis) | D1: Recommended action | E1: Expected business impact
A2: Which region has the highest sales and profit? | B2: PivotTable by Region; sort Sales and Profit descending.
A3: Which category has high sales but weak margin? | B3: Category sales and profit; calculate profit margin.
A4: Which sales channel produces the best average order value? | B4: Channel rows; Sales sum / Order count.
A5: What is the monthly sales trend and year-over-year change? | B5: Month + Year PivotTable; compare matching months.
A6: What is the return rate by product/category? | B6: COUNTIFS(Returned,Yes) / order count by category.
A7: Do delayed orders correlate with returns or lower profit? | B7: Compare Delivery_Status with Returned and Profit.
A8: Which customer segment contributes most profit? | B8: Segment-level sales, profit, margin and order count.

Sheet Data_Dictionary
A1: Field | B1: Meaning | C1: Type | D1: Business use
A2: Order_ID | B2: Unique transaction identifier | C2: Text | D2: Count orders; lookup key
A3: Order_Date | B3: Transaction date | C3: Date | D3: Trend and seasonality
A4: Region / City | B4: Geographic sales area | C4: Text | D4: Regional performance
A5: Customer_Segment | B5: Consumer, Corporate, Small Business, Education | C5: Category | D5: Segment comparison
A6: Sales_Channel | B6: Online, Retail Store, Partner, Direct Sales | C6: Category | D6: Channel effectiveness
A7: Category / Product | B7: Product hierarchy | C7: Category/Text | D7: Product mix and profitability
A8: Quantity | B8: Units sold | C8: Integer | D8: Volume analysis
A9: Unit_Price | B9: Price before discount | C9: Currency | D9: Pricing analysis
A10: Discount_Rate | B10: Discount as decimal percentage | C10: Percentage | D10: Discount effectiveness
A11: Sales | B11: Quantity × Unit Price × (1 − Discount) | C11: Currency | D11: Net sales
A12: Cost | B12: Estimated product cost | C12: Currency | D12: Cost analysis
... A20: Delivery_Status | B20: Fast / On Time / Delayed | C20: Category | D20: Service performance
