Workbook

Sheet Dashboard
A1: SALES PERFORMANCE DASHBOARD
A2: Portfolio Project | Excel Analytics | Dataset: 1,500 orders | Period: Jan–Dec 2025
A4: TOTAL SALES | D4: TOTAL PROFIT | G4: TOTAL ORDERS | J4: AVG ORDER VALUE | M4: PROFIT MARGIN
A5: =SUM(Cleaned_Data!L2:L1501) | D5: =SUM(Cleaned_Data!N2:N1501) | G5: =COUNTA(Cleaned_Data!A2:A1501) | J5: =IFERROR(SUM(Cleaned_Data!L2:L1501)/COUNTA(Cleaned_Data!A2:A1501),0) | M5: =IFERROR(SUM(Cleaned_Data!N2:N1501)/SUM(Cleaned_Data!L2:L1501),0)
A9: Monthly Performance | E9: Sales by Region | I9: Sales by Category
A10: Month | B10: Sales | C10: Profit | E10: Region | F10: Sales | G10: Profit | I10: Category | J10: Sales
A11: Jan | B11: =SUMIF(Cleaned_Data!R$2:R$1501,A11,Cleaned_Data!L$2:L$1501) | C11: =SUMIF(Cleaned_Data!R$2:R$1501,A11,Cleaned_Data!N$2:N$1501) | E11: North | F11: =SUMIF(Cleaned_Data!C$2:C$1501,E11,Cleaned_Data!L$2:L$1501) | G11: =SUMIF(Cleaned_Data!C$2:C$1501,E11,Cleaned_Data!N$2:N$1501) | I11: Technology | J11: =SUMIF(Cleaned_Data!G$2:G$1501,I11,Cleaned_Data!L$2:L$1501)
A12: Feb | B12: =SUMIF(Cleaned_Data!R$2:R$1501,A12,Cleaned_Data!L$2:L$1501) | C12: =SUMIF(Cleaned_Data!R$2:R$1501,A12,Cleaned_Data!N$2:N$1501) | E12: South | F12: =SUMIF(Cleaned_Data!C$2:C$1501,E12,Cleaned_Data!L$2:L$1501) | G12: =SUMIF(Cleaned_Data!C$2:C$1501,E12,Cleaned_Data!N$2:N$1501) | I12: Furniture | J12: =SUMIF(Cleaned_Data!G$2:G$1501,I12,Cleaned_Data!L$2:L$1501)
A13: Mar | B13: =SUMIF(Cleaned_Data!R$2:R$1501,A13,Cleaned_Data!L$2:L$1501) | C13: =SUMIF(Cleaned_Data!R$2:R$1501,A13,Cleaned_Data!N$2:N$1501) | E13: East | F13: =SUMIF(Cleaned_Data!C$2:C$1501,E13,Cleaned_Data!L$2:L$1501) | G13: =SUMIF(Cleaned_Data!C$2:C$1501,E13,Cleaned_Data!N$2:N$1501) | I13: Office Supplies | J13: =SUMIF(Cleaned_Data!G$2:G$1501,I13,Cleaned_Data!L$2:L$1501)
A14: Apr | B14: =SUMIF(Cleaned_Data!R$2:R$1501,A14,Cleaned_Data!L$2:L$1501) | C14: =SUMIF(Cleaned_Data!R$2:R$1501,A14,Cleaned_Data!N$2:N$1501) | E14: West | F14: =SUMIF(Cleaned_Data!C$2:C$1501,E14,Cleaned_Data!L$2:L$1501) | G14: =SUMIF(Cleaned_Data!C$2:C$1501,E14,Cleaned_Data!N$2:N$1501)
A15: May | B15: =SUMIF(Cleaned_Data!R$2:R$1501,A15,Cleaned_Data!L$2:L$1501) | C15: =SUMIF(Cleaned_Data!R$2:R$1501,A15,Cleaned_Data!N$2:N$1501) | E15: Central | F15: =SUMIF(Cleaned_Data!C$2:C$1501,E15,Cleaned_Data!L$2:L$1501) | G15: =SUMIF(Cleaned_Data!C$2:C$1501,E15,Cleaned_Data!N$2:N$1501)
A16: Jun | B16: =SUMIF(Cleaned_Data!R$2:R$1501,A16,Cleaned_Data!L$2:L$1501) | C16: =SUMIF(Cleaned_Data!R$2:R$1501,A16,Cleaned_Data!N$2:N$1501)
A17: Jul | B17: =SUMIF(Cleaned_Data!R$2:R$1501,A17,Cleaned_Data!L$2:L$1501) | C17: =SUMIF(Cleaned_Data!R$2:R$1501,A17,Cleaned_Data!N$2:N$1501)
A18: Aug | B18: =SUMIF(Cleaned_Data!R$2:R$1501,A18,Cleaned_Data!L$2:L$1501) | C18: =SUMIF(Cleaned_Data!R$2:R$1501,A18,Cleaned_Data!N$2:N$1501)
A19: Sep | B19: =SUMIF(Cleaned_Data!R$2:R$1501,A19,Cleaned_Data!L$2:L$1501) | C19: =SUMIF(Cleaned_Data!R$2:R$1501,A19,Cleaned_Data!N$2:N$1501)
A20: Oct | B20: =SUMIF(Cleaned_Data!R$2:R$1501,A20,Cleaned_Data!L$2:L$1501) | C20: =SUMIF(Cleaned_Data!R$2:R$1501,A20,Cleaned_Data!N$2:N$1501)
A21: Nov | B21: =SUMIF(Cleaned_Data!R$2:R$1501,A21,Cleaned_Data!L$2:L$1501) | C21: =SUMIF(Cleaned_Data!R$2:R$1501,A21,Cleaned_Data!N$2:N$1501)
A22: Dec | B22: =SUMIF(Cleaned_Data!R$2:R$1501,A22,Cleaned_Data!L$2:L$1501) | C22: =SUMIF(Cleaned_Data!R$2:R$1501,A22,Cleaned_Data!N$2:N$1501)

Sheet Raw_Data
A1: Order_ID | B1: Order_Date | C1: Region | D1: City | E1: Customer_Segment | F1: Sales_Channel | G1: Category | H1: Product | I1: Quantity | J1: Unit_Price | K1: Discount_Rate | L1: Sales | M1: Cost | N1: Profit | O1: Payment_Method | P1: Sales_Rep
A2: ORD-2511-0001 | B2: 45985 | C2: North | D2: Delhi | E2: Small Business | F2: Partner | G2: Office Supplies | H2: Paper Ream | I2: 2 | J2: 435.89 | K2: 0 | L2: 871.78 | M2: 671.27 | N2: 200.51 | O2: Cash | P2: Diya Patel
A3: ORD-2510-0002 | B3: 45960 | C3: West | D3: Mumbai | E3: Small Business | F3: Online | G3: Technology | H3: Laptop | I3: 1 | J3: 42685.57 | K3: 0 | L3: 42685.57 | M3: 37563.3 | N3: 5122.27 | O3: Cash | P3: Vivaan Gupta
A4: ORD-2504-0003 | B4: 45770 | C4: West | D4: Ahmedabad | E4: Corporate | F4: Retail Store | G4: Office Supplies | H4: File Folder | I4: 5 | J4: 85.1 | K4: 0.1 | L4: 382.95 | M4: 263.81 | N4: 119.14 | O4: Net Banking | P4: Kabir Singh
A5: ORD-2504-0004 | B5: 45768 | C5: East | D5: Kolkata | E5: Corporate | F5: Online | G5: Technology | H5: Monitor | I5: 2 | J5: 12187.91 | K5: 0.05 | L5: 23157.03 | M5: 19988.17 | N5: 3168.86 | O5: Debit Card | P5: Diya Patel
A6: ORD-2507-0005 | B6: 45851 | C6: North | D6: Chandigarh | E6: Consumer | F6: Partner | G6: Office Supplies | H6: Stapler | I6: 3 | J6: 254.24 | K6: 0.15 | L6: 648.31 | M6: 533.9 | N6: 114.41 | O6: Credit Card | P6: Aarav Sharma
A7: ORD-2512-0006 | B7: 45996 | C7: South | D7: Hyderabad | E7: Corporate | F7: Partner | G7: Technology | H7: Monitor | I7: 5 | J7: 12260.25 | K7: 0.15 | L7: 52106.06 | M7: 50267.03 | N7: 1839.03 | O7: Net Banking | P7: Kabir Singh
A8: ORD-2507-0007 | B8: 45847 | C8: East | D8: Patna | E8: Small Business | F8: Partner | G8: Office Supplies | H8: Pens Box | I8: 2 | J8: 184.26 | K8: 0.15 | L8: 313.24 | M8: 239.54 | N8: 73.7 | O8: UPI | P8: Meera Joshi
A9: ORD-2503-0008 | B9: 45741 | C9: West | D9: Surat | E9: Small Business | F9: Retail Store | G9: Technology | H9: Headphones | I9: 10 | J9: 2220.05 | K9: 0.1 | L9: 19980.45 | M9: 17316.39 | N9: 2664.06 | O9: Credit Card | P9: Meera Joshi
A10: ORD-2501-0009 | B10: 45674 | C10: East | D10: Guwahati | E10: Small Business | F10: Retail Store | G10: Technology | H10: Headphones | I10: 1 | J10: 2223.65 | K10: 0.15 | L10: 1890.1 | M10: 1734.45 | N10: 155.65 | O10: UPI | P10: Anaya Rao
A11: ORD-2507-0010 | B11: 45860 | C11: West | D11: Pune | E11: Small Business | F11: Partner | G11: Technology | H11: Headphones | I11: 1 | J11: 2213.72 | K11: 0.1 | L11: 1992.35 | M11: 1726.7 | N11: 265.65 | O11: Debit Card | P11: Vivaan Gupta
A12: ORD-2507-0011 | B12: 45843 | C12: South | D12: Chennai | E12: Consumer | F12: Partner | G12: Furniture | H12: Storage Cabinet | I12: 3 | J12: 9414.21 | K12: 0.1 | L12: 25418.37 | M12: 22594.1 | N12: 2824.27 | O12: UPI | P12: Vivaan Gupta
A13: ORD-2511-0012 | B13: 45963 | C13: North | D13: Lucknow | E13: Small Business | F13: Online | G13: Furniture | H13: Desk | I13: 3 | J13: 11042.6 | K13: 0.05 | L13: 31471.41 | M13: 25177.13 | N13: 6294.28 | O13: Credit Card | P13: Rohan Verma
... A1501: ORD-2508-1500 | B1501: 45882 | C1501: West | D1501: Surat | E1501: Small Business | F1501: Partner | G1501: Office Supplies | H1501: File Folder | I1501: 3 | J1501: 90.69 | K1501: 0.1 | L1501: 244.86 | M1501: 168.68 | N1501: 76.18 | O1501: Cash | P1501: Diya Patel

Sheet Cleaned_Data
A1: Order_ID | B1: Order_Date | C1: Region | D1: City | E1: Customer_Segment | F1: Sales_Channel | G1: Category | H1: Product | I1: Quantity | J1: Unit_Price | K1: Discount_Rate | L1: Sales | M1: Cost | N1: Profit | O1: Payment_Method | P1: Sales_Rep | Q1: Year | R1: Month | S1: Profit_Margin
A2: =Raw_Data!A2 | B2: =Raw_Data!B2 | C2: =Raw_Data!C2 | D2: =Raw_Data!D2 | E2: =Raw_Data!E2 | F2: =Raw_Data!F2 | G2: =Raw_Data!G2 | H2: =Raw_Data!H2 | ... P2: =Raw_Data!P2 | Q2: =YEAR(B2) | R2: =TEXT(B2,"mmm") | S2: =IFERROR(N2/L2,0)
A3: =Raw_Data!A3 | B3: =Raw_Data!B3 | C3: =Raw_Data!C3 | D3: =Raw_Data!D3 | E3: =Raw_Data!E3 | F3: =Raw_Data!F3 | G3: =Raw_Data!G3 | H3: =Raw_Data!H3 | ... P3: =Raw_Data!P3 | Q3: =YEAR(B3) | R3: =TEXT(B3,"mmm") | S3: =IFERROR(N3/L3,0)
A4: =Raw_Data!A4 | B4: =Raw_Data!B4 | C4: =Raw_Data!C4 | D4: =Raw_Data!D4 | E4: =Raw_Data!E4 | F4: =Raw_Data!F4 | G4: =Raw_Data!G4 | H4: =Raw_Data!H4 | ... P4: =Raw_Data!P4 | Q4: =YEAR(B4) | R4: =TEXT(B4,"mmm") | S4: =IFERROR(N4/L4,0)
A5: =Raw_Data!A5 | B5: =Raw_Data!B5 | C5: =Raw_Data!C5 | D5: =Raw_Data!D5 | E5: =Raw_Data!E5 | F5: =Raw_Data!F5 | G5: =Raw_Data!G5 | H5: =Raw_Data!H5 | ... P5: =Raw_Data!P5 | Q5: =YEAR(B5) | R5: =TEXT(B5,"mmm") | S5: =IFERROR(N5/L5,0)
A6: =Raw_Data!A6 | B6: =Raw_Data!B6 | C6: =Raw_Data!C6 | D6: =Raw_Data!D6 | E6: =Raw_Data!E6 | F6: =Raw_Data!F6 | G6: =Raw_Data!G6 | H6: =Raw_Data!H6 | ... P6: =Raw_Data!P6 | Q6: =YEAR(B6) | R6: =TEXT(B6,"mmm") | S6: =IFERROR(N6/L6,0)
A7: =Raw_Data!A7 | B7: =Raw_Data!B7 | C7: =Raw_Data!C7 | D7: =Raw_Data!D7 | E7: =Raw_Data!E7 | F7: =Raw_Data!F7 | G7: =Raw_Data!G7 | H7: =Raw_Data!H7 | ... P7: =Raw_Data!P7 | Q7: =YEAR(B7) | R7: =TEXT(B7,"mmm") | S7: =IFERROR(N7/L7,0)
A8: =Raw_Data!A8 | B8: =Raw_Data!B8 | C8: =Raw_Data!C8 | D8: =Raw_Data!D8 | E8: =Raw_Data!E8 | F8: =Raw_Data!F8 | G8: =Raw_Data!G8 | H8: =Raw_Data!H8 | ... P8: =Raw_Data!P8 | Q8: =YEAR(B8) | R8: =TEXT(B8,"mmm") | S8: =IFERROR(N8/L8,0)
A9: =Raw_Data!A9 | B9: =Raw_Data!B9 | C9: =Raw_Data!C9 | D9: =Raw_Data!D9 | E9: =Raw_Data!E9 | F9: =Raw_Data!F9 | G9: =Raw_Data!G9 | H9: =Raw_Data!H9 | ... P9: =Raw_Data!P9 | Q9: =YEAR(B9) | R9: =TEXT(B9,"mmm") | S9: =IFERROR(N9/L9,0)
A10: =Raw_Data!A10 | B10: =Raw_Data!B10 | C10: =Raw_Data!C10 | D10: =Raw_Data!D10 | E10: =Raw_Data!E10 | F10: =Raw_Data!F10 | G10: =Raw_Data!G10 | H10: =Raw_Data!H10 | ... P10: =Raw_Data!P10 | Q10: =YEAR(B10) | R10: =TEXT(B10,"mmm") | S10: =IFERROR(N10/L10,0)
A11: =Raw_Data!A11 | B11: =Raw_Data!B11 | C11: =Raw_Data!C11 | D11: =Raw_Data!D11 | E11: =Raw_Data!E11 | F11: =Raw_Data!F11 | G11: =Raw_Data!G11 | H11: =Raw_Data!H11 | ... P11: =Raw_Data!P11 | Q11: =YEAR(B11) | R11: =TEXT(B11,"mmm") | S11: =IFERROR(N11/L11,0)
A12: =Raw_Data!A12 | B12: =Raw_Data!B12 | C12: =Raw_Data!C12 | D12: =Raw_Data!D12 | E12: =Raw_Data!E12 | F12: =Raw_Data!F12 | G12: =Raw_Data!G12 | H12: =Raw_Data!H12 | ... P12: =Raw_Data!P12 | Q12: =YEAR(B12) | R12: =TEXT(B12,"mmm") | S12: =IFERROR(N12/L12,0)
A13: =Raw_Data!A13 | B13: =Raw_Data!B13 | C13: =Raw_Data!C13 | D13: =Raw_Data!D13 | E13: =Raw_Data!E13 | F13: =Raw_Data!F13 | G13: =Raw_Data!G13 | H13: =Raw_Data!H13 | ... P13: =Raw_Data!P13 | Q13: =YEAR(B13) | R13: =TEXT(B13,"mmm") | S13: =IFERROR(N13/L13,0)
... A1501: =Raw_Data!A1501 | B1501: =Raw_Data!B1501 | C1501: =Raw_Data!C1501 | D1501: =Raw_Data!D1501 | E1501: =Raw_Data!E1501 | F1501: =Raw_Data!F1501 | G1501: =Raw_Data!G1501 | H1501: =Raw_Data!H1501 | ... P1501: =Raw_Data!P1501 | Q1501: =YEAR(B1501) | R1501: =TEXT(B1501,"mmm") | S1501: =IFERROR(N1501/L1501,0)

Sheet Project_Guide
A1: PROJECT GUIDE: SALES PERFORMANCE ANALYSIS
A2: Step | B2: Task | C2: How to do it / Formula | D2: Expected output
A3: 1. Understand | B3: Review the dataset | C3: Check 1,500 orders, dates, regions, products, sales, cost and profit. | D3: Know each field and its business meaning.
A4: 2. Validate | B4: Check duplicate Order_IDs | C4: Data > Remove Duplicates, or use =COUNTIF(A:A,A2)>1 in a helper column. | D4: No duplicate order identifiers.
A5: 3. Clean | B5: Check blanks and data types | C5: Filter each column for blanks; ensure Order_Date is a date, Discount_Rate is %, and currency fields are numeric. | D5: Consistent, analysis-ready data.
A6: 4. Calculate | B6: Profit margin | C6: =IFERROR([@Profit]/[@Sales],0) in an Excel Table. | D6: Profit as a share of sales.
A7: 5. KPI | B7: Total sales | C7: =SUM(SalesClean[Sales]) | D7: Total revenue across all orders.
A8: 6. KPI | B8: Total profit | C8: =SUM(SalesClean[Profit]) | D8: Total gross profit estimate.
A9: 7. KPI | B9: Average order value | C9: =IFERROR(SUM(SalesClean[Sales])/COUNTA(SalesClean[Order_ID]),0) | D9: Average revenue per transaction.
A10: 8. Analyze | B10: Sales by region | C10: Insert > PivotTable; Rows=Region; Values=Sum of Sales, Sum of Profit. | D10: Compare regional performance.
A11: 9. Analyze | B11: Monthly trend | C11: PivotTable Rows=Order_Date grouped by Months; Values=Sum of Sales and Profit. | D11: Find seasonality and peak months.
A12: 10. Analyze | B12: Category performance | C12: PivotTable Rows=Category; Values=Sales, Profit; add Profit_Margin if useful. | D12: Identify category revenue and margin mix.
A13: 11. Dashboard | B13: Build visuals | C13: Use line chart for monthly sales, bar chart for region, column/bar chart for category; add slicers for Region, Category, Sales_Channel. | D13: Interactive management summary.
A14: 12. Validate | B14: Reconcile totals | C14: Compare dashboard totals to =SUM(Cleaned_Data!L2:L1501) and =SUM(Cleaned_Data!N2:N1501). | D14: Dashboard numbers match source data.
A15: 13. Communicate | B15: Write 3 findings | C15: Rank top region, top category, best month, and compare profit margin. | D15: Recommendations backed by data.

Sheet Formula_Practice
A1: Practice Task | B1: Formula / Answer | C1: What it does
A2: Total Sales | B2: =SUM(Cleaned_Data!L2:L1501) | C2: Adds sales revenue.
A3: Total Profit | B3: =SUM(Cleaned_Data!N2:N1501) | C3: Adds profit.
A4: Total Orders | B4: =COUNTA(Cleaned_Data!A2:A1501) | C4: Counts order IDs.
A5: Average Order Value | B5: =AVERAGE(Cleaned_Data!L2:L1501) | C5: Average sales per order.
A6: North Region Sales | B6: =SUMIF(Cleaned_Data!C2:C1501,"North",Cleaned_Data!L2:L1501) | C6: Adds sales where Region is North.
A7: Technology Category Profit | B7: =SUMIF(Cleaned_Data!G2:G1501,"Technology",Cleaned_Data!N2:N1501) | C7: Adds profit for Technology.
A8: Orders with discount > 10% | B8: =COUNTIF(Cleaned_Data!K2:K1501,">0.1") | C8: Counts orders with discounts above 10%.
A9: Profit margin overall | B9: =IFERROR(SUM(Cleaned_Data!N2:N1501)/SUM(Cleaned_Data!L2:L1501),0) | C9: Profit divided by sales.
A10: Lookup product by Order ID | B10: =XLOOKUP(A2,Cleaned_Data!A:A,Cleaned_Data!H:H,"Not Found") | C10: Returns the product for an entered order ID.
A11: Flag high-value order | B11: =IF(L2>=10000,"High Value","Standard") | C11: Labels orders using a sales threshold.

Sheet Insights_Template
A1: Question | B1: How to answer | C1: Write your finding here
A2: Which region generated the most sales? | B2: Sort the Sales by Region summary from largest to smallest.
A3: Which category generated the most profit? | B3: Create a PivotTable: Rows=Category; Values=Sum of Profit; sort descending.
A4: Which month had the highest sales? | B4: Sort Monthly Performance by Sales descending.
A5: What is the overall profit margin? | B5: Total Profit / Total Sales. Compare margin across regions and categories.
A6: Which channel performs best? | B6: PivotTable: Rows=Sales_Channel; Values=Sum of Sales, Sum of Profit, Count of Order_ID.
A7: What action would you recommend? | B7: Tie one recommendation to a measured trend, then state the expected business benefit.
